nonebot_plugin_text_ban/__init__.py
nonebot_plugin_text_ban/config.py
nonebot_plugin_text_ban-0.1.6.dist-info/METADATA
nonebot_plugin_text_ban-0.1.6.dist-info/WHEEL
nonebot_plugin_text_ban-0.1.6.dist-info/top_level.txt
nonebot_plugin_text_ban-0.1.6.dist-info/RECORD
