Metadata-Version: 2.1
Name: nonebot-plugin-text-ban
Version: 0.1.6
Summary: Default template for PDM package
Author-email: zhongwen-4 <2401128923@qq.com>
License: MIT
Requires-Python: >=3.10.0
Requires-Dist: nonebot2>=2.4.0
Requires-Dist: nonebot-adapter-onebot>=2.4.6
Requires-Dist: nonebot-plugin-localstore>=0.7.1
Requires-Dist: nonebot-plugin-alconna>=0.53.1
Requires-Dist: pypinyin>=0.53.0
